ch/__init__.py
ch/zbindenonline/__init__.py
ch/zbindenonline/weatherstation/__init__.py
ch/zbindenonline/weatherstation/config.py
ch/zbindenonline/weatherstation/domain.py
ch/zbindenonline/weatherstation/logging.py
ch/zbindenonline/weatherstation/measureRepository.py
ch/zbindenonline/weatherstation/publishMeasures.py
ch/zbindenonline/weatherstation/publishPictures.py
ch/zbindenonline/weatherstation/restServiceMeasures.py
ch/zbindenonline/weatherstation/restServicePictures.py
ch/zbindenonline/weatherstation/saveMeasures.py
ch/zbindenonline/weatherstation/sensorService.py
tests/__init__.py
tests/ch/__init__.py
tests/ch/zbindenonline/__init__.py
tests/ch/zbindenonline/weatherstation/__init__.py
tests/ch/zbindenonline/weatherstation/mocks.py
tests/ch/zbindenonline/weatherstation/test_MeasureRepository.py
tests/ch/zbindenonline/weatherstation/test_config.py
tests/ch/zbindenonline/weatherstation/test_publishMeasures.py
tests/ch/zbindenonline/weatherstation/test_publishPictures.py
tests/ch/zbindenonline/weatherstation/test_restServiceMeasures.py
tests/ch/zbindenonline/weatherstation/test_restServicePictures.py
tests/ch/zbindenonline/weatherstation/test_saveMeasures.py
tests/ch/zbindenonline/weatherstation/test_sensorService.py
tests/ch/zbindenonline/weatherstation/util.py
ch.zbindenonline.weatherstation-1.7.3.dist-info/LICENSE
ch.zbindenonline.weatherstation-1.7.3.dist-info/METADATA
ch.zbindenonline.weatherstation-1.7.3.dist-info/WHEEL
ch.zbindenonline.weatherstation-1.7.3.dist-info/entry_points.txt
ch.zbindenonline.weatherstation-1.7.3.dist-info/top_level.txt
ch.zbindenonline.weatherstation-1.7.3.dist-info/RECORD
