Metadata-Version: 2.1
Name: ch.zbindenonline.weatherstation
Version: 1.7.3
Summary: Collects data from tinkerforge outdoor weather station and saves it to sqlite database.
Home-page: UNKNOWN
Author: Patrick Zbinden
License: MIT
Platform: UNKNOWN
Classifier: Programming Language :: Python :: 3
Requires-Python: >=3.9
License-File: LICENSE
Requires-Dist: requests
Requires-Dist: click
Requires-Dist: tinkerforge
